selenium_fb_group_automator/__init__.py
selenium_fb_group_automator/cli.py
selenium_fb_group_automator/selenium_fb_group_automator.py
selenium_fb_group_automator-0.1.1.dist-info/AUTHORS.rst
selenium_fb_group_automator-0.1.1.dist-info/LICENSE
selenium_fb_group_automator-0.1.1.dist-info/METADATA
selenium_fb_group_automator-0.1.1.dist-info/WHEEL
selenium_fb_group_automator-0.1.1.dist-info/entry_points.txt
selenium_fb_group_automator-0.1.1.dist-info/top_level.txt
selenium_fb_group_automator-0.1.1.dist-info/RECORD
