Metadata-Version: 2.1
Name: selenium-fb-group-automator
Version: 0.1.1
Summary: Manage Facebook Groups using Selenium
Home-page: https://github.com/prince-mishra/selenium_fb_group_automator
Author: Prince Mishra
Author-email: indiandexter007@gmai.com
License: MIT license
Keywords: selenium_fb_group_automator
Platform: UNKNOWN
Classifier: Development Status :: 2 - Pre-Alpha
Classifier: Intended Audience :: Developers
Classifier: License :: OSI Approved :: MIT License
Classifier: Natural Language :: English
Classifier: Programming Language :: Python :: 3
Classifier: Programming Language :: Python :: 3.5
Classifier: Programming Language :: Python :: 3.6
Classifier: Programming Language :: Python :: 3.7
Classifier: Programming Language :: Python :: 3.8
Requires-Python: >=3.5
